simpar_cli/__init__.py
simpar_cli/__main__.py
simpar_cli/exception.py
simpar_cli/simpar.py
simpar_cli-0.0.12.dist-info/LICENSE
simpar_cli-0.0.12.dist-info/METADATA
simpar_cli-0.0.12.dist-info/WHEEL
simpar_cli-0.0.12.dist-info/entry_points.txt
simpar_cli-0.0.12.dist-info/top_level.txt
simpar_cli-0.0.12.dist-info/RECORD
